leetcode_export/__init__.py
leetcode_export/__main__.py
leetcode_export/_version.py
leetcode_export/leetcode.py
leetcode_export/leetcode_graphql.py
leetcode_export/leetcode_rest.py
leetcode_export/utils.py
leetcode_export-2.4.0.dist-info/LICENSE
leetcode_export-2.4.0.dist-info/METADATA
leetcode_export-2.4.0.dist-info/WHEEL
leetcode_export-2.4.0.dist-info/entry_points.txt
leetcode_export-2.4.0.dist-info/top_level.txt
leetcode_export-2.4.0.dist-info/RECORD
