Metadata-Version: 2.1
Name: leetcode-export
Version: 2.4.0
Summary: Python script to export your LeetCode solutions
Home-page: https://github.com/NeverMendel/leetcode-export
Author: Davide Cazzin
Author-email: 28535750+NeverMendel@users.noreply.github.com
License: MIT
Keywords: leetcode,leetcode-solutions,leetcode-export
Classifier: Programming Language :: Python :: 3
Classifier: Programming Language :: Python :: 3.8
Classifier: License :: OSI Approved :: MIT License
Classifier: Operating System :: OS Independent
Requires-Python: >=3.7
License-File: LICENSE
Requires-Dist: dataclasses-json
Requires-Dist: requests
